{"is_source_file": true, "format": "JavaScript (React JSX)", "description": "React component for displaying and managing a shopping cart, including item listing, quantity adjustments, total calculation, and navigation links.", "external_files": ["../contexts/CartContext", "../utils/format"], "external_methods": ["useCart", "formatCurrency"], "published": ["Cart"], "classes": [], "methods": [{"name": "Cart()", "description": "Functional React component rendering the shopping cart interface with item management and navigation.", "scope": "", "scopeKind": ""}], "calls": ["useCart", "formatCurrency", "items.map", "updateQuantity", "removeFromCart", "clearCart"], "search-terms": ["Cart.jsx", "shopping cart React component", "useCart hook", "formatCurrency utility", "item quantity management", "checkout link"], "state": 2, "file_id": 25, "knowledge_revision": 56, "git_revision": "", "ctags": [{"_type": "tag", "name": "Cart", "path": "/home/kavia/workspace/code-generation/online-shopping-platform-125854-125863/shopping_app_frontend/src/pages/Cart.jsx", "pattern": "/^export default function Cart() {$/", "language": "JavaScript", "kind": "function", "signature": "()"}], "hash": "ad21e50c6b01627e05937e495877e6a6", "format-version": 4, "code-base-name": "shopping_app_frontend", "filename": "shopping_app_frontend/src/pages/Cart.jsx", "revision_history": [{"56": ""}]}